{"version":2,"kind":"Notebook","sha256":"341fa6bc96dc411b164c3e92ed7c5eace9e14e5a9251b9356d1cbdc13b49bbc5","slug":"notebooks.templates.prereqs-templates","location":"/notebooks/templates/prereqs-templates.ipynb","dependencies":[],"frontmatter":{"title":"Templates","content_includes_title":false,"kernelspec":{"name":"python3","display_name":"Python 3 (ipykernel)","language":"python"},"authors":[{"nameParsed":{"literal":"Wolfgang Wagner","given":"Wolfgang","family":"Wagner"},"name":"Wolfgang Wagner","id":"contributors-myst-generated-uid-0"},{"nameParsed":{"literal":"Martin Schobben","given":"Martin","family":"Schobben"},"name":"Martin Schobben","id":"contributors-myst-generated-uid-1"},{"nameParsed":{"literal":"Nikolas Pikall","given":"Nikolas","family":"Pikall"},"name":"Nikolas Pikall","id":"contributors-myst-generated-uid-2"},{"nameParsed":{"literal":"Joseph Wagner","given":"Joseph","family":"Wagner"},"name":"Joseph Wagner","id":"contributors-myst-generated-uid-3"},{"nameParsed":{"literal":"Davide Festa","given":"Davide","family":"Festa"},"name":"Davide Festa","id":"contributors-myst-generated-uid-4"},{"nameParsed":{"literal":"Felix David Reuß","given":"Felix David","family":"Reuß"},"name":"Felix David Reuß","id":"contributors-myst-generated-uid-5"},{"nameParsed":{"literal":"Luka Jović","given":"Luka","family":"Jović"},"name":"Luka Jović","id":"contributors-myst-generated-uid-6"}],"open_access":true,"license":{"content":{"id":"Apache-2.0","url":"https://opensource.org/licenses/Apache-2.0","name":"Apache License 2.0","free":true,"osi":true},"code":{"id":"CC-BY-4.0","url":"https://creativecommons.org/licenses/by/4.0/","name":"Creative Commons Attribution 4.0 International","free":true,"CC":true}},"copyright":"2024","numbering":{"title":{"offset":1}},"exports":[{"format":"ipynb","filename":"prereqs-templates.ipynb","url":"/eo-datascience-cookbook/build/prereqs-templates-f6db73e432dee8b46b8043ff6718c6f7.ipynb"}]},"widgets":{},"mdast":{"type":"root","children":[{"type":"block","kind":"notebook-content","children":[{"type":"paragraph","position":{"start":{"line":4,"column":1},"end":{"line":6,"column":1}},"children":[{"type":"text","value":"This section of the Cookbook covers a wide range of topics. The intent is to\ncreate templates to showcase workflows that can be used by students as a primer\nfor independent research projects.","position":{"start":{"line":4,"column":1},"end":{"line":4,"column":1}},"key":"i8kb76thly"}],"key":"hwbKjTJsNn"},{"type":"table","position":{"start":{"line":8,"column":1},"end":{"line":14,"column":1}},"children":[{"type":"tableRow","position":{"start":{"line":8,"column":1},"end":{"line":8,"column":1}},"children":[{"type":"tableCell","header":true,"position":{"start":{"line":8,"column":1},"end":{"line":8,"column":1}},"children":[{"type":"text","value":"Concepts","position":{"start":{"line":8,"column":1},"end":{"line":8,"column":1}},"key":"VGpy8G2Oj7"}],"key":"SeH3R3iCtZ"},{"type":"tableCell","header":true,"position":{"start":{"line":8,"column":1},"end":{"line":8,"column":1}},"children":[{"type":"text","value":"Importance","position":{"start":{"line":8,"column":1},"end":{"line":8,"column":1}},"key":"shAGQSWPdh"}],"key":"wRWa8xx1p6"},{"type":"tableCell","header":true,"position":{"start":{"line":8,"column":1},"end":{"line":8,"column":1}},"children":[{"type":"text","value":"Notes","position":{"start":{"line":8,"column":1},"end":{"line":8,"column":1}},"key":"u6cxNrrJn6"}],"key":"ofdOa4oRJ1"}],"key":"TvL2s3mU0K"},{"type":"tableRow","position":{"start":{"line":10,"column":1},"end":{"line":10,"column":1}},"children":[{"type":"tableCell","position":{"start":{"line":10,"column":1},"end":{"line":10,"column":1}},"children":[{"type":"link","url":"https://foundations.projectpythia.org/core/xarray/xarray-intro.html","position":{"start":{"line":10,"column":1},"end":{"line":10,"column":1}},"children":[{"type":"text","value":"Intro to xarray","position":{"start":{"line":10,"column":1},"end":{"line":10,"column":1}},"key":"CwyWuF19so"}],"urlSource":"https://foundations.projectpythia.org/core/xarray/xarray-intro.html","key":"rFuGLsSM2d"}],"key":"xaAtnmIrCz"},{"type":"tableCell","position":{"start":{"line":10,"column":1},"end":{"line":10,"column":1}},"children":[{"type":"text","value":"Necessary","position":{"start":{"line":10,"column":1},"end":{"line":10,"column":1}},"key":"L6q2iVFvap"}],"key":"fMXD2fJ74u"},{"type":"tableCell","position":{"start":{"line":10,"column":1},"end":{"line":10,"column":1}},"children":[],"key":"AJu3nLzozC"}],"key":"XmfJZcXSng"},{"type":"tableRow","position":{"start":{"line":11,"column":1},"end":{"line":11,"column":1}},"children":[{"type":"tableCell","position":{"start":{"line":11,"column":1},"end":{"line":11,"column":1}},"children":[{"type":"link","url":"https://foundations.projectpythia.org/core/xarray/dask-arrays-xarray.html","position":{"start":{"line":11,"column":1},"end":{"line":11,"column":1}},"children":[{"type":"text","value":"Dask Arrays","position":{"start":{"line":11,"column":1},"end":{"line":11,"column":1}},"key":"iDDBXPsK3S"}],"urlSource":"https://foundations.projectpythia.org/core/xarray/dask-arrays-xarray.html","key":"xoGsFxG1Pu"}],"key":"WvYQcDpfvI"},{"type":"tableCell","position":{"start":{"line":11,"column":1},"end":{"line":11,"column":1}},"children":[{"type":"text","value":"Necessary","position":{"start":{"line":11,"column":1},"end":{"line":11,"column":1}},"key":"XkZVnAhLwn"}],"key":"wmkyfP4uGv"},{"type":"tableCell","position":{"start":{"line":11,"column":1},"end":{"line":11,"column":1}},"children":[],"key":"VGQ4BkoK7h"}],"key":"kSprRM8i0o"},{"type":"tableRow","position":{"start":{"line":12,"column":1},"end":{"line":12,"column":1}},"children":[{"type":"tableCell","position":{"start":{"line":12,"column":1},"end":{"line":12,"column":1}},"children":[{"type":"link","url":"https://scikit-learn.org/stable/","position":{"start":{"line":12,"column":1},"end":{"line":12,"column":1}},"children":[{"type":"text","value":"Documentation scikit-learn","position":{"start":{"line":12,"column":1},"end":{"line":12,"column":1}},"key":"aE88AONBbD"}],"urlSource":"https://scikit-learn.org/stable/","key":"Ql2iPKcaVC"}],"key":"Pjtidv9Tsg"},{"type":"tableCell","position":{"start":{"line":12,"column":1},"end":{"line":12,"column":1}},"children":[{"type":"text","value":"Neccesary","position":{"start":{"line":12,"column":1},"end":{"line":12,"column":1}},"key":"MQ7VNQxJZs"}],"key":"sn3EJPsN8D"},{"type":"tableCell","position":{"start":{"line":12,"column":1},"end":{"line":12,"column":1}},"children":[{"type":"text","value":"Machine Learning in Python","position":{"start":{"line":12,"column":1},"end":{"line":12,"column":1}},"key":"IWKoI2LjV9"}],"key":"UctAsZpjge"}],"key":"gZCm9XTrvD"},{"type":"tableRow","position":{"start":{"line":13,"column":1},"end":{"line":13,"column":1}},"children":[{"type":"tableCell","position":{"start":{"line":13,"column":1},"end":{"line":13,"column":1}},"children":[{"type":"link","url":"https://matplotlib.org/stable/users/explain/quick_start.html","position":{"start":{"line":13,"column":1},"end":{"line":13,"column":1}},"children":[{"type":"text","value":"Documentation Matplotlib","position":{"start":{"line":13,"column":1},"end":{"line":13,"column":1}},"key":"NbdCWIKSQ1"}],"urlSource":"https://matplotlib.org/stable/users/explain/quick_start.html","key":"ZvcbtozdJi"}],"key":"wAM345qTLz"},{"type":"tableCell","position":{"start":{"line":13,"column":1},"end":{"line":13,"column":1}},"children":[{"type":"text","value":"Helpful","position":{"start":{"line":13,"column":1},"end":{"line":13,"column":1}},"key":"gjgIAMivpB"}],"key":"SA5i7CVLc8"},{"type":"tableCell","position":{"start":{"line":13,"column":1},"end":{"line":13,"column":1}},"children":[{"type":"text","value":"Ploting in Python","position":{"start":{"line":13,"column":1},"end":{"line":13,"column":1}},"key":"hDNaiSIT7e"}],"key":"NtlRi3NPbf"}],"key":"yH9ud6XQBN"},{"type":"tableRow","position":{"start":{"line":14,"column":1},"end":{"line":14,"column":1}},"children":[{"type":"tableCell","position":{"start":{"line":14,"column":1},"end":{"line":14,"column":1}},"children":[{"type":"link","url":"https://odc-stac.readthedocs.io/en/latest/","position":{"start":{"line":14,"column":1},"end":{"line":14,"column":1}},"children":[{"type":"text","value":"Documentation odc-stac","position":{"start":{"line":14,"column":1},"end":{"line":14,"column":1}},"key":"XecK1HIiwJ"}],"urlSource":"https://odc-stac.readthedocs.io/en/latest/","key":"nTIZKACtJa"}],"key":"G9GJnr5xU7"},{"type":"tableCell","position":{"start":{"line":14,"column":1},"end":{"line":14,"column":1}},"children":[{"type":"text","value":"Helpful","position":{"start":{"line":14,"column":1},"end":{"line":14,"column":1}},"key":"DbZO1dpeG5"}],"key":"DHJgmSOQy8"},{"type":"tableCell","position":{"start":{"line":14,"column":1},"end":{"line":14,"column":1}},"children":[{"type":"text","value":"Data access","position":{"start":{"line":14,"column":1},"end":{"line":14,"column":1}},"key":"VlPiBYUS0v"}],"key":"QVp3DtrLMv"}],"key":"PJLULsEKwt"}],"key":"UgaRMQgeoX"},{"type":"list","ordered":false,"spread":false,"position":{"start":{"line":16,"column":1},"end":{"line":16,"column":1}},"children":[{"type":"listItem","spread":true,"position":{"start":{"line":16,"column":1},"end":{"line":16,"column":1}},"children":[{"type":"strong","position":{"start":{"line":16,"column":1},"end":{"line":16,"column":1}},"children":[{"type":"text","value":"Time to learn","position":{"start":{"line":16,"column":1},"end":{"line":16,"column":1}},"key":"VMMujCUKGf"}],"key":"aKXAi032Cl"},{"type":"text","value":": 10 min","position":{"start":{"line":16,"column":1},"end":{"line":16,"column":1}},"key":"LYBN7Jn0Ka"}],"key":"ffUPybkLiU"}],"key":"p13KGKqrsO"}],"key":"uJJV2FoOTx"}],"key":"mew0ZCoW5x"},"references":{"cite":{"order":[],"data":{}}},"footer":{"navigation":{"prev":{"title":"Microwave Remote Sensing","url":"/notebooks/courses/microwave-remote-sensing","group":"Courses"},"next":{"title":"Classification of Sentinel-2 imagery","url":"/notebooks/templates/classification","group":"Templates"}}},"domain":"http://localhost:3000"}