{"version":2,"kind":"Notebook","sha256":"d50db674b19b15dbd94fdee530e8f646b0c9e843c606569d6aada4edd50534d3","slug":"notebooks.courses.environmental-remote-sensing","location":"/notebooks/courses/environmental-remote-sensing.ipynb","dependencies":[],"frontmatter":{"title":"Environmental Remote Sensing","content_includes_title":false,"kernelspec":{"name":"python3","display_name":"Python 3 (ipykernel)","language":"python"},"authors":[{"nameParsed":{"literal":"Wolfgang Wagner","given":"Wolfgang","family":"Wagner"},"name":"Wolfgang Wagner","id":"contributors-myst-generated-uid-0"},{"nameParsed":{"literal":"Martin Schobben","given":"Martin","family":"Schobben"},"name":"Martin Schobben","id":"contributors-myst-generated-uid-1"},{"nameParsed":{"literal":"Nikolas Pikall","given":"Nikolas","family":"Pikall"},"name":"Nikolas Pikall","id":"contributors-myst-generated-uid-2"},{"nameParsed":{"literal":"Joseph Wagner","given":"Joseph","family":"Wagner"},"name":"Joseph Wagner","id":"contributors-myst-generated-uid-3"},{"nameParsed":{"literal":"Davide Festa","given":"Davide","family":"Festa"},"name":"Davide Festa","id":"contributors-myst-generated-uid-4"},{"nameParsed":{"literal":"Felix David Reuß","given":"Felix David","family":"Reuß"},"name":"Felix David Reuß","id":"contributors-myst-generated-uid-5"},{"nameParsed":{"literal":"Luka Jović","given":"Luka","family":"Jović"},"name":"Luka Jović","id":"contributors-myst-generated-uid-6"}],"open_access":true,"license":{"content":{"id":"CC-BY-4.0","url":"https://creativecommons.org/licenses/by/4.0/","name":"Creative Commons Attribution 4.0 International","free":true,"CC":true},"code":{"id":"Apache-2.0","url":"https://opensource.org/licenses/Apache-2.0","name":"Apache License 2.0","free":true,"osi":true}},"copyright":"2024","affiliations":[{"id":"UAlbany","name":"University at Albany (SUNY)","department":"Atmospheric and Environmental Sciences","url":"https://www.albany.edu/daes"},{"id":"CISL","name":"NSF National Center for Atmospheric Research","department":"Computational and Information Systems Lab","url":"https://www.cisl.ucar.edu"},{"id":"Unidata","name":"NSF Unidata","url":"https://www.unidata.ucar.edu"},{"id":"Argonne","name":"Argonne National Laboratory","department":"Environmental Science Division","url":"https://www.anl.gov/evs"},{"id":"CarbonPlan","name":"CarbonPlan","url":"https://carbonplan.org"},{"id":"NVIDIA","name":"NVIDIA Corporation","url":"https://www.nvidia.com/"}],"numbering":{"title":{"offset":1}},"exports":[{"format":"ipynb","filename":"environmental-remote-sensing.ipynb","url":"/eo-datascience-cookbook/build/environmental-remote-0886af77bc8d4a2f553a44bbe0909192.ipynb"}]},"widgets":{},"mdast":{"type":"root","children":[{"type":"block","kind":"notebook-content","children":[{"type":"paragraph","position":{"start":{"line":4,"column":1},"end":{"line":4,"column":1}},"children":[{"type":"text","value":"These course materials where developed in the framework of the DrySat project: ","position":{"start":{"line":4,"column":1},"end":{"line":4,"column":1}},"key":"JQPnCBWgB2"},{"type":"emphasis","position":{"start":{"line":4,"column":1},"end":{"line":4,"column":1}},"children":[{"type":"text","value":"Enhancing Drought Early Warning in Mozambique through Satellite Soil Moisture Data to support food security in the context of climate change","position":{"start":{"line":4,"column":1},"end":{"line":4,"column":1}},"key":"lKWEyYjtH2"}],"key":"RW2buTfU0t"},{"type":"text","value":".","position":{"start":{"line":4,"column":1},"end":{"line":4,"column":1}},"key":"Vy2aiANCPK"}],"key":"ct3DKkHW8E"},{"type":"heading","depth":2,"position":{"start":{"line":6,"column":1},"end":{"line":6,"column":1}},"children":[{"type":"text","value":"Prerequisites","position":{"start":{"line":6,"column":1},"end":{"line":6,"column":1}},"key":"DHY4wiWz9Z"}],"identifier":"prerequisites","label":"Prerequisites","html_id":"prerequisites","implicit":true,"key":"IorEYyMiqO"},{"type":"table","position":{"start":{"line":8,"column":1},"end":{"line":12,"column":1}},"children":[{"type":"tableRow","position":{"start":{"line":8,"column":1},"end":{"line":8,"column":1}},"children":[{"type":"tableCell","header":true,"position":{"start":{"line":8,"column":1},"end":{"line":8,"column":1}},"children":[{"type":"text","value":"Concepts","position":{"start":{"line":8,"column":1},"end":{"line":8,"column":1}},"key":"PXDySAHSv0"}],"key":"jfCnncN4oX"},{"type":"tableCell","header":true,"position":{"start":{"line":8,"column":1},"end":{"line":8,"column":1}},"children":[{"type":"text","value":"Importance","position":{"start":{"line":8,"column":1},"end":{"line":8,"column":1}},"key":"WGNqyrc2an"}],"key":"PjWfOQmKkX"},{"type":"tableCell","header":true,"position":{"start":{"line":8,"column":1},"end":{"line":8,"column":1}},"children":[{"type":"text","value":"Notes","position":{"start":{"line":8,"column":1},"end":{"line":8,"column":1}},"key":"U87bnJL80E"}],"key":"uGwS3v9jWU"}],"key":"MvrXz0EKlQ"},{"type":"tableRow","position":{"start":{"line":10,"column":1},"end":{"line":10,"column":1}},"children":[{"type":"tableCell","position":{"start":{"line":10,"column":1},"end":{"line":10,"column":1}},"children":[{"type":"link","url":"https://projectpythia.org/eo-datascience-cookbook/README.html","position":{"start":{"line":10,"column":1},"end":{"line":10,"column":1}},"children":[{"type":"text","value":"Intro to Earth Observation Data Science","position":{"start":{"line":10,"column":1},"end":{"line":10,"column":1}},"key":"TBwa86m163"}],"urlSource":"https://projectpythia.org/eo-datascience-cookbook/README.html","key":"RS6WULIflL"}],"key":"jRKR0qFXn1"},{"type":"tableCell","position":{"start":{"line":10,"column":1},"end":{"line":10,"column":1}},"children":[{"type":"text","value":"Helpful","position":{"start":{"line":10,"column":1},"end":{"line":10,"column":1}},"key":"oXnFdrFcqE"}],"key":"QOoM7NZBgg"},{"type":"tableCell","position":{"start":{"line":10,"column":1},"end":{"line":10,"column":1}},"children":[],"key":"Ia2JaMmIj7"}],"key":"oTizkPfFJZ"},{"type":"tableRow","position":{"start":{"line":11,"column":1},"end":{"line":11,"column":1}},"children":[{"type":"tableCell","position":{"start":{"line":11,"column":1},"end":{"line":11,"column":1}},"children":[{"type":"link","url":"https://hvplot.holoviz.org/","position":{"start":{"line":11,"column":1},"end":{"line":11,"column":1}},"children":[{"type":"text","value":"Documentation hvPlot","position":{"start":{"line":11,"column":1},"end":{"line":11,"column":1}},"key":"g7xwGS6eIH"}],"urlSource":"https://hvplot.holoviz.org/","key":"Gpbk2at7vI"}],"key":"uSIeaFWAWL"},{"type":"tableCell","position":{"start":{"line":11,"column":1},"end":{"line":11,"column":1}},"children":[{"type":"text","value":"Helpful","position":{"start":{"line":11,"column":1},"end":{"line":11,"column":1}},"key":"cwvU5VTB6d"}],"key":"iXrL0wrTP3"},{"type":"tableCell","position":{"start":{"line":11,"column":1},"end":{"line":11,"column":1}},"children":[{"type":"text","value":"Interactive plotting","position":{"start":{"line":11,"column":1},"end":{"line":11,"column":1}},"key":"wlmYkZiaUI"}],"key":"H7xicz9INk"}],"key":"OrXwOiTEdS"},{"type":"tableRow","position":{"start":{"line":12,"column":1},"end":{"line":12,"column":1}},"children":[{"type":"tableCell","position":{"start":{"line":12,"column":1},"end":{"line":12,"column":1}},"children":[{"type":"link","url":"https://pandas.pydata.org/","position":{"start":{"line":12,"column":1},"end":{"line":12,"column":1}},"children":[{"type":"text","value":"Documentation pandas","position":{"start":{"line":12,"column":1},"end":{"line":12,"column":1}},"key":"hYQoKGRmIX"}],"urlSource":"https://pandas.pydata.org/","key":"NGx54bMy7k"}],"key":"nmc14vlo1l"},{"type":"tableCell","position":{"start":{"line":12,"column":1},"end":{"line":12,"column":1}},"children":[{"type":"text","value":"Helpful","position":{"start":{"line":12,"column":1},"end":{"line":12,"column":1}},"key":"pLlrKPGXf5"}],"key":"IJBUtQIKzu"},{"type":"tableCell","position":{"start":{"line":12,"column":1},"end":{"line":12,"column":1}},"children":[{"type":"text","value":"Tabular data wrangling","position":{"start":{"line":12,"column":1},"end":{"line":12,"column":1}},"key":"xPN5VHj3xe"}],"key":"YvnmGzlDDA"}],"key":"ywLH3IOYt9"}],"key":"d7AkAg4ldp"},{"type":"list","ordered":false,"spread":false,"position":{"start":{"line":14,"column":1},"end":{"line":15,"column":1}},"children":[{"type":"listItem","spread":true,"position":{"start":{"line":14,"column":1},"end":{"line":15,"column":1}},"children":[{"type":"paragraph","children":[{"type":"strong","position":{"start":{"line":14,"column":1},"end":{"line":14,"column":1}},"children":[{"type":"text","value":"Time to learn","position":{"start":{"line":14,"column":1},"end":{"line":14,"column":1}},"key":"sk3ddMUA1O"}],"key":"GutqU8g4lW"},{"type":"text","value":": 90 min","position":{"start":{"line":14,"column":1},"end":{"line":14,"column":1}},"key":"jca0V6L7bP"}],"key":"N15lZo2BQg"}],"key":"O6YwVLl3YM"}],"key":"LsLPVhyfEj"},{"type":"admonition","kind":"note","children":[{"type":"admonitionTitle","children":[{"type":"text","value":"Note","key":"XZBlIFdAiJ"}],"key":"rjsRpf0s98"},{"type":"paragraph","position":{"start":{"line":17,"column":1},"end":{"line":18,"column":1}},"children":[{"type":"text","value":"These notebooks contain interactive elements. The full interactive elements can\nonly be viewed on Binder by clicking on the Binder badge or 🚀 button.","position":{"start":{"line":17,"column":1},"end":{"line":17,"column":1}},"key":"rnC0K5a4Jj"}],"key":"EKOEljLoPv"}],"key":"uYJXrcuaE8"}],"key":"FNKwK95FYf"}],"key":"rZe4MVfTLw"},"references":{"cite":{"order":[],"data":{}}},"footer":{"navigation":{"prev":{"title":"Phase Unwrapping","url":"/notebooks/courses/microwave-remote-sensing/unit-03/in-class-exercise-2","group":"Courses"},"next":{"title":"Remotely Sensed Droughts in Mozambique","url":"/notebooks/courses/environmental-remote-sensing/unit-01/handout-drought","group":"Courses"}}},"domain":"http://localhost:3000"}